<?xml version="1.0" encoding="utf-8"?><LanguageData>

    <SculptingSpeed.label>billedhugnings hastighed</SculptingSpeed.label>
    <SculptingSpeed.description>Hastigheden denne karakter laver skulpture.</SculptingSpeed.description>

    <TailoringSpeed.label>synings hastighed</TailoringSpeed.label>
    <TailoringSpeed.description>Hastigheden denne karakter laver tøj.</TailoringSpeed.description>

    <SmithingSpeed.label>smednings hastighed</SmithingSpeed.label>
    <SmithingSpeed.description>Hastigheden denne person vil smede våben, maksiner, ammunition og værktøjer.</SmithingSpeed.description>

    <DrugProductionSpeed.label>medicin produktion hastighed</DrugProductionSpeed.label>
    <DrugProductionSpeed.description>Hvor hutgitgt denne karakter producere medicin.</DrugProductionSpeed.description>

    <CookSpeed.label>madlavnings hastighed</CookSpeed.label>
    <CookSpeed.description>Hastigheden denne person vil lave mad.</CookSpeed.description>

    <FoodPoisonChance.label>madforgiftnings chance</FoodPoisonChance.label>
    <FoodPoisonChance.description>Sandsynligheden at denne karakter vil utilsigtet forgifte et tilberedt måltid.</FoodPoisonChance.description>

    <BrewingSpeed.label>brygnings hastighed</BrewingSpeed.label>
    <BrewingSpeed.description>Hastigheden denne person kan brygge øl.</BrewingSpeed.description>

    <ButcheryFleshSpeed.label>slagte hastighed</ButcheryFleshSpeed.label>
    <ButcheryFleshSpeed.description>Hastigheden denne person skære kødet fra væsner.</ButcheryFleshSpeed.description>

    <ButcheryFleshEfficiency.label>slagteri effektivitet</ButcheryFleshEfficiency.label>
    <ButcheryFleshEfficiency.description>Ganger mængden af kød der er produceret når der slagtes dyr.</ButcheryFleshEfficiency.description>

    <ButcheryMechanoidSpeed.label>mekanit demonterings hastighed </ButcheryMechanoidSpeed.label>
    <ButcheryMechanoidSpeed.description>Hastigheden denne person demonterer en mekanit.</ButcheryMechanoidSpeed.description>

    <ButcheryMechanoidEfficiency.label>mekanit demontering effektivitet</ButcheryMechanoidEfficiency.label>
    <ButcheryMechanoidEfficiency.description>Ganger mængden af materiale der fåes når denne person demonterer en død mekanit.</ButcheryMechanoidEfficiency.description>

    <StonecuttingSpeed.label>stenhugnings hastighed</StonecuttingSpeed.label>
    <StonecuttingSpeed.description>Hastigheden denne person skære rå sten til blokke.</StonecuttingSpeed.description>

    <SmeltingSpeed.label>smeltnings hastighed</SmeltingSpeed.label>
    <SmeltingSpeed.description>Hastigheden denne person smelter ting.</SmeltingSpeed.description>

</LanguageData>