<?xml version="1.0" encoding="utf-8" ?>
<LanguageData>

<UnfinishedSculpture.label>ufærdig skulptur</UnfinishedSculpture.label>
<UnfinishedGun.label>ufærdig pistol</UnfinishedGun.label>
<UnfinishedWeapon.label>ufærdigt våben</UnfinishedWeapon.label>
<UnfinishedArmor.label>ufærdig rustning</UnfinishedArmor.label>
<UnfinishedTechArmor.label>ufærdig rustning</UnfinishedTechArmor.label>
<UnfinishedMetallicTechArmor.label>ufærdig rustning</UnfinishedMetallicTechArmor.label>
<UnfinishedApparel.label>ufærdigt tøj</UnfinishedApparel.label>
<UnfinishedBelt.label>ufærdigt belte</UnfinishedBelt.label>
<UnfinishedComponent.label>ufærdigt komponent</UnfinishedComponent.label>


  <!-- ======================= Minified things ========================= -->

<MinifiedThing.label>minificeret genstand</MinifiedThing.label>


</LanguageData>